cdk_ecrpublic_gc/__init__.py
cdk_ecrpublic_gc/py.typed
cdk_ecrpublic_gc/_jsii/__init__.py
cdk_ecrpublic_gc/_jsii/cdk-ecrpublic-gc@0.1.175.jsii.tgz
cdk_ecrpublic_gc-0.1.175.dist-info/LICENSE
cdk_ecrpublic_gc-0.1.175.dist-info/METADATA
cdk_ecrpublic_gc-0.1.175.dist-info/WHEEL
cdk_ecrpublic_gc-0.1.175.dist-info/top_level.txt
cdk_ecrpublic_gc-0.1.175.dist-info/RECORD
