Metadata-Version: 2.1
Name: cdk-ecrpublic-gc
Version: 0.1.175
Summary: Garbage collector for Amazon ECR public
Home-page: https://github.com/pahudnet/cdk-ecrpublic-gc.git
Author: Pahud Hsieh<pahudnet@gmail.com>
License: Apache-2.0
Project-URL: Source, https://github.com/pahudnet/cdk-ecrpublic-gc.git
Platform: UNKNOWN
Classifier: Intended Audience :: Developers
Classifier: Operating System :: OS Independent
Classifier: Programming Language :: JavaScript
Classifier: Programming Language :: Python :: 3 :: Only
Classifier: Programming Language :: Python :: 3.6
Classifier: Programming Language :: Python :: 3.7
Classifier: Programming Language :: Python :: 3.8
Classifier: Programming Language :: Python :: 3.9
Classifier: Typing :: Typed
Classifier: Development Status :: 5 - Production/Stable
Classifier: License :: OSI Approved
Requires-Python: >=3.6
License-File: LICENSE
Requires-Dist: aws-cdk.aws-events-targets (<2.0.0,>=1.95.1)
Requires-Dist: aws-cdk.aws-events (<2.0.0,>=1.95.1)
Requires-Dist: aws-cdk.aws-iam (<2.0.0,>=1.95.1)
Requires-Dist: aws-cdk.aws-lambda-nodejs (<2.0.0,>=1.95.1)
Requires-Dist: aws-cdk.aws-lambda (<2.0.0,>=1.95.1)
Requires-Dist: aws-cdk.aws-stepfunctions-tasks (<2.0.0,>=1.95.1)
Requires-Dist: aws-cdk.aws-stepfunctions (<2.0.0,>=1.95.1)
Requires-Dist: aws-cdk.core (<2.0.0,>=1.95.1)
Requires-Dist: constructs (<4.0.0,>=3.2.27)
Requires-Dist: jsii (<2.0.0,>=1.46.0)
Requires-Dist: publication (>=0.0.3)
